hmd_cli_repo/__init__.py
hmd_cli_repo/controller.py
hmd_cli_repo/hmd_cli_repo.py
hmd_cli_repo/loaders/__init__.py
hmd_cli_repo/loaders/project_template_loader.py
hmd_cli_repo/loaders/project_type_loader.py
hmd_cli_repo/project_types/Bender Integration Tests.prj_type.json
hmd_cli_repo/project_types/CDKTF Repo Class.prj_type.json
hmd_cli_repo/project_types/CLI Command.prj_type.json
hmd_cli_repo/project_types/Cluster Config.prj_type.json
hmd_cli_repo/project_types/Docker Image.prj_type.json
hmd_cli_repo/project_types/Documentation.prj_type.json
hmd_cli_repo/project_types/Helm Repo Class.prj_type.json
hmd_cli_repo/project_types/Language Pack.prj_type.json
hmd_cli_repo/project_types/Librarian Content Item Types.prj_type.json
hmd_cli_repo/project_types/Librarian.prj_type.json
hmd_cli_repo/project_types/Mickey Configuration.prj_type.json
hmd_cli_repo/project_types/Mickey Templates.prj_type.json
hmd_cli_repo/project_types/Microservice With Language Pack.prj_type.json
hmd_cli_repo/project_types/Microservice.prj_type.json
hmd_cli_repo/project_types/Notebook Analytics.prj_type.json
hmd_cli_repo/project_types/Notebook Transform.prj_type.json
hmd_cli_repo/project_types/Python Library.prj_type.json
hmd_cli_repo/project_types/SQL Analytics.prj_type.json
hmd_cli_repo/project_types/Transform Config.prj_type.json
hmd_cli_repo/project_types/Transform Image.prj_type.json
hmd_cli_repo/pt/cc/meta-data/VERSION
hmd_cli_repo/pt/cc/meta-data/manifest.json
hmd_cli_repo/pt/cc/src/cutters/backstage_backend_plugin_repo/cookiecutter.json
hmd_cli_repo/pt/cc/src/cutters/backstage_backend_plugin_repo/{{cookiecutter.repo_name}}/src/typescript/.prettierrc
hmd_cli_repo/pt/cc/src/cutters/backstage_backend_plugin_repo/{{cookiecutter.repo_name}}/src/typescript/package.json
hmd_cli_repo/pt/cc/src/cutters/backstage_backend_plugin_repo/{{cookiecutter.repo_name}}/src/typescript/src/index.ts
hmd_cli_repo/pt/cc/src/cutters/backstage_backend_plugin_repo/{{cookiecutter.repo_name}}/src/typescript/src/run.ts
hmd_cli_repo-0.3.149.dist-info/METADATA
hmd_cli_repo-0.3.149.dist-info/WHEEL
hmd_cli_repo-0.3.149.dist-info/entry_points.txt
hmd_cli_repo-0.3.149.dist-info/top_level.txt
hmd_cli_repo-0.3.149.dist-info/RECORD
